stackspot/__init__.py
stackspot/stackspot.py
stackspot/stackspot_ai.py
stackspot/stackspot_ai_ks.py
stackspot/stackspot_ai_quick_command.py
stackspot/stackspot_auth.py
stackspot/stackspot_dict_types.py
stackspot-1.0.1.dist-info/LICENSE
stackspot-1.0.1.dist-info/METADATA
stackspot-1.0.1.dist-info/WHEEL
stackspot-1.0.1.dist-info/top_level.txt
stackspot-1.0.1.dist-info/RECORD
