Metadata-Version: 2.1
Name: stackspot
Version: 1.0.1
Summary: Stackspot API bindings for Python
Home-page: https://github.com/Potentii/stackspot-python
Author: Guilherme Reginaldo Ruella
Author-email: potentii@gmail.com
License-File: LICENSE
Requires-Dist: requests==2.32.3
